matrix_enum/__init__.py
matrix_enum/matrix_enum.py
matrix_enum-1.1.0.dist-info/LICENSE
matrix_enum-1.1.0.dist-info/METADATA
matrix_enum-1.1.0.dist-info/WHEEL
matrix_enum-1.1.0.dist-info/top_level.txt
matrix_enum-1.1.0.dist-info/RECORD
