Metadata-Version: 2.1
Name: matrix-enum
Version: 1.1.0
Summary: Data structure for multi-dimensional enums
Home-page: https://github.com/klaviyo/matrix_enum
Author: Klaviyo
Author-email: maintainers@klaviyo.com
License: MIT
Keywords: enum
Platform: UNKNOWN
Classifier: Development Status :: 5 - Production/Stable
Classifier: Intended Audience :: Developers
Classifier: License :: OSI Approved :: MIT License
Classifier: Natural Language :: English
Classifier: Programming Language :: Python :: 2
Classifier: Programming Language :: Python :: 2.7
Classifier: Programming Language :: Python :: 3
Classifier: Programming Language :: Python :: 3.4
Classifier: Programming Language :: Python :: 3.5
Classifier: Programming Language :: Python :: 3.6
Classifier: Programming Language :: Python :: 3.7
Classifier: Programming Language :: Python :: Implementation :: CPython
Classifier: Programming Language :: Python :: Implementation :: PyPy
Classifier: Programming Language :: Python
Classifier: Topic :: Software Development :: Libraries :: Python Modules
Classifier: Topic :: Utilities
Requires-Python: >=2.7, !=3.0.*, !=3.1.*, !=3.2.*, !=3.3.*, <4
Requires-Dist: six (>=1.12)
Requires-Dist: enum34 (>=1.1.6) ; python_version < "3.4"
Provides-Extra: dev
Requires-Dist: tox (~=3.13) ; extra == 'dev'
